{
  "@type": "Interface",
  "@id": "dtmi:jacdac:services:x1f37c56a;1",
  "displayName": "Character Screen",
  "description": "A screen that displays characters.",
  "contents": [
    {
      "@type": "Property",
      "name": "message",
      "@id": "dtmi:jacdac:x1f37c56a:rw:message;1",
      "description": "Text to show. Use `\\n` to break lines.",
      "schema": "string",
      "writable": true
    },
    {
      "@type": "Property",
      "name": "brightness",
      "@id": "dtmi:jacdac:x1f37c56a:rw:brightness;1",
      "description": "Brightness of the screen. `0` means off.",
      "schema": "float",
      "writable": true
    },
    {
      "@type": "Property",
      "name": "variant",
      "@id": "dtmi:jacdac:x1f37c56a:const:variant;1",
      "description": "Describes the type of character LED screen.",
      "schema": "dtmi:jacdac:x1f37c56a:variant;1"
    },
    {
      "@type": "Property",
      "name": "text_direction",
      "@id": "dtmi:jacdac:x1f37c56a:rw:textdirection;1",
      "description": "Specifies the RTL or LTR direction of the text.",
      "schema": "dtmi:jacdac:x1f37c56a:textdirection;1",
      "writable": true
    },
    {
      "@type": "Property",
      "name": "rows",
      "@id": "dtmi:jacdac:x1f37c56a:const:rows;1",
      "description": "Gets the number of rows.",
      "schema": "integer"
    },
    {
      "@type": "Property",
      "name": "columns",
      "@id": "dtmi:jacdac:x1f37c56a:const:columns;1",
      "description": "Gets the number of columns.",
      "schema": "integer"
    }
  ],
  "extends": [
    "dtmi:jacdac:services:x1ffffff3;1"
  ],
  "schemas": [
    {
      "@id": "dtmi:jacdac:x1f37c56a:event;1",
      "@type": "Object",
      "fields": [
        {
          "name": "count",
          "schema": "integer"
        }
      ]
    },
    {
      "@type": "Enum",
      "@id": "dtmi:jacdac:x1f37c56a:variant;1",
      "valueSchema": "integer",
      "enumValues": [
        {
          "name": "lCD",
          "displayName": "LCD",
          "enumValue": 1
        },
        {
          "name": "oLED",
          "displayName": "OLED",
          "enumValue": 2
        }
      ]
    },
    {
      "@type": "Enum",
      "@id": "dtmi:jacdac:x1f37c56a:textdirection;1",
      "valueSchema": "integer",
      "enumValues": [
        {
          "name": "leftToRight",
          "displayName": "LeftToRight",
          "enumValue": 1
        },
        {
          "name": "rightToLeft",
          "displayName": "RightToLeft",
          "enumValue": 2
        }
      ]
    }
  ],
  "@context": "dtmi:dtdl:context;2"
}